md2video/__init__.py
md2video/__main__.py
md2video/md2image.py
md2video/md2slidemd.py
md2video/server.py
md2video/slide.py
md2video/tts/__init__.py
md2video/tts/kokoro.py
md2video/utils.py
md2video-0.0.1.dist-info/METADATA
md2video-0.0.1.dist-info/WHEEL
md2video-0.0.1.dist-info/RECORD
