Metadata-Version: 2.3
Name: md2video
Version: 0.0.1
Summary: Convert markdown presentations files to video
License: MIT
Author: am009
Author-email: 634960348@qq.com
Requires-Python: >=3.9
Classifier: Programming Language :: Python :: 3
Classifier: Operating System :: OS Independent
Project-URL: Homepage, https://github.com/am009/md2video
Project-URL: Issues, https://github.com/am009/md2video/issues
